py_nifcloud/__init__.py
py_nifcloud/auth.py
py_nifcloud/computing_client.py
py_nifcloud/computing_util.py
py_nifcloud/nifcloud_client.py
py_nifcloud-1.0.0.dist-info/DESCRIPTION.rst
py_nifcloud-1.0.0.dist-info/METADATA
py_nifcloud-1.0.0.dist-info/RECORD
py_nifcloud-1.0.0.dist-info/WHEEL
py_nifcloud-1.0.0.dist-info/metadata.json
py_nifcloud-1.0.0.dist-info/top_level.txt
