Metadata-Version: 2.0
Name: py-nifcloud
Version: 1.0.0
Summary: Python wrapper for NifCloud
Home-page: https://github.com/o-hayato/py_nifcloud
Author: o-hayato
Author-email: preasper0+github@gmail.com
License: MIT
Platform: UNKNOWN
Classifier: Development Status :: 4 - Beta
Classifier: Environment :: Web Environment
Classifier: Intended Audience :: Developers
Classifier: License :: OSI Approved :: MIT License
Classifier: Programming Language :: Python
Classifier: Programming Language :: Python :: 3.4
Classifier: Programming Language :: Python :: 3.5
Classifier: Programming Language :: Python :: 3.6
Classifier: Topic :: Software Development
Requires-Dist: requests
Requires-Dist: PyYAML
Requires-Dist: botocore
Requires-Dist: beautifulsoup4
Provides-Extra: dev
Requires-Dist: pytest (>=3); extra == 'dev'
Requires-Dist: coverage; extra == 'dev'
Requires-Dist: tox; extra == 'dev'
Requires-Dist: sphinx; extra == 'dev'
Requires-Dist: jupyter; extra == 'dev'
Requires-Dist: lxml; extra == 'dev'
Requires-Dist: pallets-sphinx-themes; extra == 'dev'
Requires-Dist: sphinxcontrib-log-cabinet; extra == 'dev'
